pyside6_to_apk/__init__.py
pyside6_to_apk/build_Android.py
pyside6_to_apk/build_Linux.py
pyside6_to_apk/main.py
pyside6_to_apk/main.ui
pyside6_to_apk/spec_editor.txt
pyside6_to_apk/ui_main.py
pyside6_to_apk-1.0.0.dist-info/METADATA
pyside6_to_apk-1.0.0.dist-info/WHEEL
pyside6_to_apk-1.0.0.dist-info/entry_points.txt
pyside6_to_apk-1.0.0.dist-info/top_level.txt
pyside6_to_apk-1.0.0.dist-info/RECORD
