Metadata-Version: 2.4
Name: PySide6-to-apk
Version: 1.0.0
Summary: Effortlessly build and package your PySide6 apps for Linux and Android apks — no command-line struggles, just a beautiful GUI!
Home-page: https://github.com/Nishant2009/PySide6-to-apk
Author: Nishant Pratap Savita
License: MIT
Project-URL: Source, https://github.com/Nishant2009/PySide6-to-apk
Project-URL: Tracker, https://github.com/Nishant2009/PySide6-to-apk/issues
Classifier: Programming Language :: Python :: 3
Classifier: License :: OSI Approved :: MIT License
Classifier: Operating System :: POSIX :: Linux
Classifier: Intended Audience :: Developers
Classifier: Topic :: Software Development :: Build Tools
Classifier: Natural Language :: English
Requires-Python: >=3.10
Requires-Dist: PySide6
Requires-Dist: PyInstaller
Requires-Dist: GitPython
Dynamic: author
Dynamic: classifier
Dynamic: description
Dynamic: description-content-type
Dynamic: home-page
Dynamic: license
Dynamic: project-url
Dynamic: requires-dist
Dynamic: requires-python
Dynamic: summary
